iaptoolkit_cli/__init__.py
iaptoolkit_cli/application.py
iaptoolkit_cli/commands/__init__.py
iaptoolkit_cli/commands/oidc.py
iaptoolkit_cli/common.py
iaptoolkit_cli/constants.py
iaptoolkit_cli/exceptions.py
iaptoolkit_cli-0.0.1a2.dist-info/LICENSE
iaptoolkit_cli-0.0.1a2.dist-info/METADATA
iaptoolkit_cli-0.0.1a2.dist-info/WHEEL
iaptoolkit_cli-0.0.1a2.dist-info/RECORD
